obsidiana/__init__.py
obsidiana/__main__.py
obsidiana/_cli.py
obsidiana/vault.py
obsidiana/tests/__init__.py
obsidiana/tests/test_integration.py
obsidiana-2025.12.1.dist-info/METADATA
obsidiana-2025.12.1.dist-info/WHEEL
obsidiana-2025.12.1.dist-info/entry_points.txt
obsidiana-2025.12.1.dist-info/licenses/COPYING
obsidiana-2025.12.1.dist-info/RECORD
