Metadata-Version: 2.4
Name: obsidiana
Version: 2025.12.1
Summary: Tools for working with Obsidian vault(s)
Project-URL: Issues, https://github.com/Julian/obsidiana/issues/
Project-URL: Funding, https://github.com/sponsors/Julian
Project-URL: Source, https://github.com/Julian/obsidiana
Author-email: Julian Berman <Julian+obsidiana@GrayVines.com>
License-Expression: MIT
License-File: COPYING
Keywords: notes,notetaking,obsidian
Classifier: Development Status :: 3 - Alpha
Classifier: Operating System :: OS Independent
Classifier: Programming Language :: Python
Classifier: Programming Language :: Python :: 3
Classifier: Programming Language :: Python :: 3.12
Classifier: Programming Language :: Python :: 3.13
Classifier: Programming Language :: Python :: 3.14
Classifier: Programming Language :: Python :: Implementation :: CPython
Classifier: Programming Language :: Python :: Implementation :: PyPy
Requires-Python: >=3.12
Requires-Dist: attrs
Requires-Dist: jsonschema[format]
Requires-Dist: python-frontmatter
Requires-Dist: rich-click
